pymc/__init__.py
pymc/_version.py
pymc/blocking.py
pymc/data.py
pymc/exceptions.py
pymc/func_utils.py
pymc/initial_point.py
pymc/math.py
pymc/model_graph.py
pymc/printing.py
pymc/pytensorf.py
pymc/testing.py
pymc/util.py
pymc/vartypes.py
pymc/backends/__init__.py
pymc/backends/arviz.py
pymc/backends/base.py
pymc/backends/mcbackend.py
pymc/backends/ndarray.py
pymc/backends/report.py
pymc/backends/zarr.py
pymc/dims/__init__.py
pymc/dims/math.py
pymc/dims/model.py
pymc/dims/distributions/__init__.py
pymc/dims/distributions/core.py
pymc/dims/distributions/scalar.py
pymc/dims/distributions/transforms.py
pymc/dims/distributions/vector.py
pymc/distributions/__init__.py
pymc/distributions/censored.py
pymc/distributions/continuous.py
pymc/distributions/custom.py
pymc/distributions/discrete.py
pymc/distributions/dist_math.py
pymc/distributions/distribution.py
pymc/distributions/mixture.py
pymc/distributions/multivariate.py
pymc/distributions/shape_utils.py
pymc/distributions/simulator.py
pymc/distributions/timeseries.py
pymc/distributions/transforms.py
pymc/distributions/truncated.py
pymc/distributions/moments/__init__.py
pymc/distributions/moments/means.py
pymc/gp/__init__.py
pymc/gp/cov.py
pymc/gp/gp.py
pymc/gp/hsgp_approx.py
pymc/gp/mean.py
pymc/gp/util.py
pymc/logprob/__init__.py
pymc/logprob/abstract.py
pymc/logprob/basic.py
pymc/logprob/binary.py
pymc/logprob/censoring.py
pymc/logprob/checks.py
pymc/logprob/cumsum.py
pymc/logprob/linalg.py
pymc/logprob/mixture.py
pymc/logprob/order.py
pymc/logprob/rewriting.py
pymc/logprob/scan.py
pymc/logprob/switch.py
pymc/logprob/tensor.py
pymc/logprob/transform_value.py
pymc/logprob/transforms.py
pymc/logprob/utils.py
pymc/model/__init__.py
pymc/model/core.py
pymc/model/fgraph.py
pymc/model/transform/__init__.py
pymc/model/transform/basic.py
pymc/model/transform/conditioning.py
pymc/model/transform/optimization.py
pymc/ode/__init__.py
pymc/ode/ode.py
pymc/ode/utils.py
pymc/plots/__init__.py
pymc/progress_bar/__init__.py
pymc-5.27.1.dist-info/licenses/LICENSE
pymc-5.27.1.dist-info/METADATA
pymc-5.27.1.dist-info/WHEEL
pymc-5.27.1.dist-info/top_level.txt
pymc-5.27.1.dist-info/RECORD
