Metadata-Version: 2.4
Name: pymc
Version: 5.27.1
Summary: Probabilistic Programming in Python: Bayesian Modeling and Probabilistic Machine Learning with PyTensor
Home-page: http://github.com/pymc-devs/pymc
Maintainer: PyMC Developers
Maintainer-email: pymc.devs@gmail.com
License: Apache License, Version 2.0
Classifier: Development Status :: 5 - Production/Stable
Classifier: Programming Language :: Python
Classifier: Programming Language :: Python :: 3
Classifier: Programming Language :: Python :: 3.11
Classifier: Programming Language :: Python :: 3.12
Classifier: Programming Language :: Python :: 3.13
Classifier: Programming Language :: Python :: 3.14
Classifier: License :: OSI Approved :: Apache Software License
Classifier: Intended Audience :: Science/Research
Classifier: Topic :: Scientific/Engineering
Classifier: Topic :: Scientific/Engineering :: Mathematics
Classifier: Operating System :: OS Independent
Requires-Python: >=3.11
License-File: LICENSE
Requires-Dist: arviz>=0.13.0
Requires-Dist: cachetools>=4.2.1
Requires-Dist: cloudpickle
Requires-Dist: numpy>=1.25.0
Requires-Dist: pandas>=0.24.0
Requires-Dist: pytensor<2.38.0,>=2.37.0
Requires-Dist: rich>=13.7.1
Requires-Dist: scipy>=1.4.1
Requires-Dist: threadpoolctl<4.0.0,>=3.1.0
Requires-Dist: typing-extensions>=3.7.4
Dynamic: classifier
Dynamic: description
Dynamic: description-content-type
Dynamic: home-page
Dynamic: license
Dynamic: license-file
Dynamic: maintainer
Dynamic: maintainer-email
Dynamic: requires-dist
Dynamic: requires-python
Dynamic: summary
